insights_python_client/__init__.py
insights_python_client/api_client.py
insights_python_client/configuration.py
insights_python_client/rest.py
insights_python_client/api/__init__.py
insights_python_client/api/boundary_api.py
insights_python_client/api/file_api.py
insights_python_client/api/metrics_api.py
insights_python_client/api/token_api.py
insights_python_client/api/weather_api.py
insights_python_client/api/yield_api.py
insights_python_client/models/__init__.py
insights_python_client/models/access_token_request.py
insights_python_client/models/access_token_response.py
insights_python_client/models/boundary_metrics.py
insights_python_client/models/boundary_response.py
insights_python_client/models/crop_detail.py
insights_python_client/models/crop_metric.py
insights_python_client/models/custom_error_response.py
insights_python_client/models/gdd.py
insights_python_client/models/metrics.py
insights_python_client/models/model_info.py
insights_python_client/models/plot_image_response.py
insights_python_client/models/satellite_metrics_response.py
insights_python_client/models/weather.py
insights_python_client/models/weather_data_response.py
insights_python_client/models/yield_response.py
insights_python_client/models/yields_data.py
test/__init__.py
test/test_access_token_request.py
test/test_access_token_response.py
test/test_boundary_api.py
test/test_boundary_metrics.py
test/test_boundary_response.py
test/test_crop_detail.py
test/test_crop_metric.py
test/test_custom_error_response.py
test/test_file_api.py
test/test_gdd.py
test/test_metrics.py
test/test_metrics_api.py
test/test_model_info.py
test/test_plot_image_response.py
test/test_satellite_metrics_response.py
test/test_token_api.py
test/test_weather.py
test/test_weather_api.py
test/test_weather_data_response.py
test/test_yield_api.py
test/test_yield_response.py
test/test_yields_data.py
insights_python_client-0.0.5.dist-info/METADATA
insights_python_client-0.0.5.dist-info/WHEEL
insights_python_client-0.0.5.dist-info/top_level.txt
insights_python_client-0.0.5.dist-info/RECORD
