Metadata-Version: 2.1
Name: insights-python-client
Version: 0.0.5
Summary: Insights Service API -test
Home-page: 
Author-email: 
Keywords: Swagger,Insights Service API -test
Requires-Dist: urllib3 (>=1.15)
Requires-Dist: six (>=1.10)
Requires-Dist: certifi
Requires-Dist: python-dateutil
